endstone_runtime.dll
endstone_runtime.pdb
manifest.json
endstone/__init__.py
endstone/__main__.py
endstone/actor.py
endstone/ban.py
endstone/block.py
endstone/boss.py
endstone/command.py
endstone/damage.py
endstone/enchantments.py
endstone/event.py
endstone/form.py
endstone/inventory.py
endstone/lang.py
endstone/level.py
endstone/map.py
endstone/permissions.py
endstone/plugin.py
endstone/scheduler.py
endstone/scoreboard.py
endstone/util.py
endstone/_internal/__init__.py
endstone/_internal/endstone_python.cp312-win_amd64.pyd
endstone/_internal/endstone_python.pyi
endstone/_internal/metrics.py
endstone/_internal/plugin_loader.py
endstone/_internal/version.py
endstone/_internal/bootstrap/__init__.py
endstone/_internal/bootstrap/base.py
endstone/_internal/bootstrap/linux.py
endstone/_internal/bootstrap/windows.py
endstone/config/endstone.toml
levistone-0.10.13.dist-info/licenses/LICENSE
levistone-0.10.13.dist-info/METADATA
levistone-0.10.13.dist-info/WHEEL
levistone-0.10.13.dist-info/entry_points.txt
levistone-0.10.13.dist-info/top_level.txt
levistone-0.10.13.dist-info/RECORD
